{
  "namespaces": [
    "public"
  ],
  "name": "public",
  "tables": [
    {
      "columns": {
        "id": {
          "name": "id",
          "type": "text",
          "unsigned": false,
          "autoincrement": false,
          "primary": false,
          "nullable": false,
          "mappedType": "text"
        },
        "state": {
          "name": "state",
          "type": "text",
          "unsigned": false,
          "autoincrement": false,
          "primary": false,
          "nullable": false,
          "mappedType": "text"
        },
        "created_at": {
          "name": "created_at",
          "type": "timestamptz",
          "unsigned": false,
          "autoincrement": false,
          "primary": false,
          "nullable": false,
          "length": 6,
          "default": "now()",
          "mappedType": "datetime"
        },
        "updated_at": {
          "name": "updated_at",
          "type": "timestamptz",
          "unsigned": false,
          "autoincrement": false,
          "primary": false,
          "nullable": false,
          "length": 6,
          "default": "now()",
          "mappedType": "datetime"
        },
        "deleted_at": {
          "name": "deleted_at",
          "type": "timestamptz",
          "unsigned": false,
          "autoincrement": false,
          "primary": false,
          "nullable": true,
          "length": 6,
          "mappedType": "datetime"
        }
      },
      "name": "wish_list_state",
      "schema": "public",
      "indexes": [
        {
          "keyName": "IDX_wish_list_state_deleted_at",
          "columnNames": [],
          "composite": false,
          "constraint": false,
          "primary": false,
          "unique": false,
          "expression": "CREATE INDEX IF NOT EXISTS \"IDX_wish_list_state_deleted_at\" ON \"wish_list_state\" (deleted_at) WHERE deleted_at IS NULL"
        },
        {
          "keyName": "wish_list_state_pkey",
          "columnNames": [
            "id"
          ],
          "composite": false,
          "constraint": true,
          "primary": true,
          "unique": true
        }
      ],
      "checks": [],
      "foreignKeys": {},
      "nativeEnums": {}
    },
    {
      "columns": {
        "id": {
          "name": "id",
          "type": "text",
          "unsigned": false,
          "autoincrement": false,
          "primary": false,
          "nullable": false,
          "mappedType": "text"
        },
        "titulo": {
          "name": "titulo",
          "type": "text",
          "unsigned": false,
          "autoincrement": false,
          "primary": false,
          "nullable": false,
          "mappedType": "text"
        },
        "state_id": {
          "name": "state_id",
          "type": "text",
          "unsigned": false,
          "autoincrement": false,
          "primary": false,
          "nullable": false,
          "mappedType": "text"
        },
        "created_at": {
          "name": "created_at",
          "type": "timestamptz",
          "unsigned": false,
          "autoincrement": false,
          "primary": false,
          "nullable": false,
          "length": 6,
          "default": "now()",
          "mappedType": "datetime"
        },
        "updated_at": {
          "name": "updated_at",
          "type": "timestamptz",
          "unsigned": false,
          "autoincrement": false,
          "primary": false,
          "nullable": false,
          "length": 6,
          "default": "now()",
          "mappedType": "datetime"
        },
        "deleted_at": {
          "name": "deleted_at",
          "type": "timestamptz",
          "unsigned": false,
          "autoincrement": false,
          "primary": false,
          "nullable": true,
          "length": 6,
          "mappedType": "datetime"
        }
      },
      "name": "wish_list",
      "schema": "public",
      "indexes": [
        {
          "keyName": "IDX_wish_list_state_id",
          "columnNames": [],
          "composite": false,
          "constraint": false,
          "primary": false,
          "unique": false,
          "expression": "CREATE INDEX IF NOT EXISTS \"IDX_wish_list_state_id\" ON \"wish_list\" (state_id) WHERE deleted_at IS NULL"
        },
        {
          "keyName": "IDX_wish_list_deleted_at",
          "columnNames": [],
          "composite": false,
          "constraint": false,
          "primary": false,
          "unique": false,
          "expression": "CREATE INDEX IF NOT EXISTS \"IDX_wish_list_deleted_at\" ON \"wish_list\" (deleted_at) WHERE deleted_at IS NULL"
        },
        {
          "keyName": "wish_list_pkey",
          "columnNames": [
            "id"
          ],
          "composite": false,
          "constraint": true,
          "primary": true,
          "unique": true
        }
      ],
      "checks": [],
      "foreignKeys": {
        "wish_list_state_id_foreign": {
          "constraintName": "wish_list_state_id_foreign",
          "columnNames": [
            "state_id"
          ],
          "localTableName": "public.wish_list",
          "referencedColumnNames": [
            "id"
          ],
          "referencedTableName": "public.wish_list_state",
          "updateRule": "cascade"
        }
      },
      "nativeEnums": {}
    }
  ],
  "nativeEnums": {}
}
